tokenwise/__init__.py
tokenwise/models/__init__.py
tokenwise/models/base.py
tokenwise/models/huggingface.py
tokenwise/quality.py
tokenwise-0.1.0.dist-info/LICENSE
tokenwise-0.1.0.dist-info/METADATA
tokenwise-0.1.0.dist-info/WHEEL
tokenwise-0.1.0.dist-info/RECORD
